{
    "openapi": "3.0.0",
    "info": {
        "title": "tdPSA API Documentation",
        "description": "API documentation for tdPSA Clients module",
        "contact": {
            "email": "support@example.com"
        },
        "license": {
            "name": "Apache 2.0",
            "url": "http://www.apache.org/licenses/LICENSE-2.0.html"
        },
        "version": "1.0.0"
    },
    "servers": [
        {
            "url": "/",
            "description": "tdPSA API Server"
        }
    ],
    "paths": {
        "/api/v1/assets": {
            "get": {
                "tags": [
                    "Assets"
                ],
                "summary": "Get list of assets",
                "description": "Returns list of assets with pagination. Can be filtered by client_id.",
                "operationId": "getAssetList",
                "parameters": [
                    {
                        "name": "client_id",
                        "in": "query",
                        "description": "Filter assets by client ID",
                        "required": false,
                        "schema": {
                            "type": "integer"
                        }
                    }
                ],
                "responses": {
                    "200": {
                        "description": "Successful operation"
                    },
                    "401": {
                        "description": "Unauthenticated"
                    }
                },
                "security": [
                    {
                        "bearerAuth": []
                    }
                ]
            }
        },
        "/api/v1/assets/{id}": {
            "get": {
                "tags": [
                    "Assets"
                ],
                "summary": "Get asset information",
                "description": "Returns detailed information for a specific asset",
                "operationId": "getAssetById",
                "parameters": [
                    {
                        "name": "id",
                        "in": "path",
                        "description": "ID of asset to return",
                        "required": true,
                        "schema": {
                            "type": "integer"
                        }
                    }
                ],
                "responses": {
                    "200": {
                        "description": "Successful operation"
                    },
                    "401": {
                        "description": "Unauthenticated"
                    },
                    "404": {
                        "description": "Asset Not Found"
                    }
                },
                "security": [
                    {
                        "bearerAuth": []
                    }
                ]
            }
        },
        "/api/v1/clients": {
            "get": {
                "tags": [
                    "Clients"
                ],
                "summary": "Get list of clients",
                "description": "Returns list of clients with pagination",
                "operationId": "getClientList",
                "responses": {
                    "200": {
                        "description": "Successful operation"
                    },
                    "401": {
                        "description": "Unauthenticated"
                    }
                },
                "security": [
                    {
                        "bearerAuth": []
                    }
                ]
            }
        },
        "/api/v1/clients/{id}": {
            "get": {
                "tags": [
                    "Clients"
                ],
                "summary": "Get client information",
                "description": "Returns client data",
                "operationId": "getClientById",
                "parameters": [
                    {
                        "name": "id",
                        "in": "path",
                        "description": "ID of client to return",
                        "required": true,
                        "schema": {
                            "type": "integer",
                            "format": "int64"
                        }
                    }
                ],
                "responses": {
                    "200": {
                        "description": "Successful operation"
                    },
                    "400": {
                        "description": "Bad Request"
                    },
                    "401": {
                        "description": "Unauthenticated"
                    },
                    "404": {
                        "description": "Resource Not Found"
                    }
                },
                "security": [
                    {
                        "bearerAuth": []
                    }
                ]
            }
        },
        "/api/v1/clients/{id}/assets": {
            "get": {
                "tags": [
                    "Clients",
                    "Assets"
                ],
                "summary": "Get client assets",
                "description": "Returns list of assets belonging to a specific client",
                "operationId": "getClientAssets",
                "parameters": [
                    {
                        "name": "id",
                        "in": "path",
                        "description": "ID of client to return assets for",
                        "required": true,
                        "schema": {
                            "type": "integer",
                            "format": "int64"
                        }
                    }
                ],
                "responses": {
                    "200": {
                        "description": "Successful operation"
                    },
                    "401": {
                        "description": "Unauthenticated"
                    },
                    "404": {
                        "description": "Client Not Found"
                    }
                },
                "security": [
                    {
                        "bearerAuth": []
                    }
                ]
            }
        }
    },
    "components": {
        "securitySchemes": {
            "bearerAuth": {
                "type": "http",
                "bearerFormat": "JWT",
                "scheme": "bearer"
            }
        }
    },
    "tags": [
        {
            "name": "Assets",
            "description": "API Endpoints for Assets"
        },
        {
            "name": "Clients",
            "description": "API Endpoints for Clients"
        }
    ]
}